{
    "key": "group_665e136beb9b1",
    "title": "Byline Fields",
    "fields": [
        {
            "key": "field_665e203c625c6",
            "label": "Display Options",
            "name": "display_options",
            "aria-label": "",
            "type": "checkbox",
            "instructions": "",
            "required": 0,
            "conditional_logic": 0,
            "wrapper": {
                "width": "",
                "class": "",
                "id": ""
            },
            "choices": {
                "display_research_partner": "Display Research Partner (Research posts only)",
                "display_publication_date": "Display Publication Date",
                "display_spotlight_authors": "Display Spotlight Author(s)"
            },
            "default_value": [
                "display_research_partner",
                "display_publication_date",
                "display_spotlight_authors"
            ],
            "return_format": "value",
            "allow_custom": 0,
            "layout": "vertical",
            "toggle": 0,
            "save_custom": 0,
            "custom_choice_button_text": "Add new choice"
        }
    ],
    "location": [
        [
            {
                "param": "block",
                "operator": "==",
                "value": "acf\/byline"
            }
        ]
    ],
    "menu_order": 0,
    "position": "normal",
    "style": "default",
    "label_placement": "top",
    "instruction_placement": "label",
    "hide_on_screen": "",
    "active": true,
    "description": "",
    "show_in_rest": 0,
    "modified": 1717447434
}
